{
  "events": [
    {
      "kind": "no_change",
      "ts": "2026-06-25T03:50:05.360065-07:00",
      "detail": {}
    },
    {
      "kind": "no_change",
      "ts": "2026-06-25T01:01:20.495473-07:00",
      "detail": {}
    },
    {
      "kind": "no_change",
      "ts": "2026-06-24T21:37:09.962519-07:00",
      "detail": {}
    },
    {
      "kind": "no_change",
      "ts": "2026-06-24T17:19:08.889168-07:00",
      "detail": {}
    },
    {
      "kind": "no_change",
      "ts": "2026-06-24T15:54:58.653771-07:00",
      "detail": {}
    },
    {
      "kind": "no_change",
      "ts": "2026-06-24T14:39:27.478108-07:00",
      "detail": {}
    },
    {
      "kind": "no_change",
      "ts": "2026-06-24T13:00:23.109357-07:00",
      "detail": {}
    },
    {
      "kind": "no_change",
      "ts": "2026-06-24T11:03:17.647983-07:00",
      "detail": {}
    },
    {
      "kind": "no_change",
      "ts": "2026-06-24T08:54:48.900243-07:00",
      "detail": {}
    },
    {
      "kind": "no_change",
      "ts": "2026-06-24T06:31:07.765290-07:00",
      "detail": {}
    }
  ]
}