{
  "events": [
    {
      "kind": "no_change",
      "ts": "2026-06-07T14:39:56.343590-07:00",
      "detail": {}
    },
    {
      "kind": "no_change",
      "ts": "2026-06-07T13:21:01.846304-07:00",
      "detail": {}
    },
    {
      "kind": "no_change",
      "ts": "2026-06-07T11:59:10.010925-07:00",
      "detail": {}
    },
    {
      "kind": "no_change",
      "ts": "2026-06-07T10:49:45.512608-07:00",
      "detail": {}
    },
    {
      "kind": "no_change",
      "ts": "2026-06-07T09:25:44.594432-07:00",
      "detail": {}
    },
    {
      "kind": "no_change",
      "ts": "2026-06-07T08:02:43.465001-07:00",
      "detail": {}
    },
    {
      "kind": "no_change",
      "ts": "2026-06-07T06:07:24.207725-07:00",
      "detail": {}
    },
    {
      "kind": "no_change",
      "ts": "2026-06-07T04:29:43.871816-07:00",
      "detail": {}
    },
    {
      "kind": "no_change",
      "ts": "2026-06-07T02:51:50.582184-07:00",
      "detail": {}
    },
    {
      "kind": "no_change",
      "ts": "2026-06-06T23:39:13.066531-07:00",
      "detail": {}
    }
  ]
}