{
  "events": [
    {
      "kind": "no_change",
      "ts": "2026-06-24T13:00:23.109357-07:00",
      "detail": {}
    },
    {
      "kind": "no_change",
      "ts": "2026-06-24T11:03:17.647983-07:00",
      "detail": {}
    },
    {
      "kind": "no_change",
      "ts": "2026-06-24T08:54:48.900243-07:00",
      "detail": {}
    },
    {
      "kind": "no_change",
      "ts": "2026-06-24T06:31:07.765290-07:00",
      "detail": {}
    },
    {
      "kind": "no_change",
      "ts": "2026-06-24T04:18:33.717025-07:00",
      "detail": {}
    },
    {
      "kind": "no_change",
      "ts": "2026-06-24T01:15:27.678679-07:00",
      "detail": {}
    },
    {
      "kind": "no_change",
      "ts": "2026-06-23T21:40:05.220469-07:00",
      "detail": {}
    },
    {
      "kind": "no_change",
      "ts": "2026-06-23T17:12:58.406649-07:00",
      "detail": {}
    },
    {
      "kind": "no_change",
      "ts": "2026-06-23T16:15:46.905262-07:00",
      "detail": {}
    },
    {
      "kind": "no_change",
      "ts": "2026-06-23T15:01:35.191834-07:00",
      "detail": {}
    }
  ]
}